{
  "kind": "collectionType",
  "collectionName": "acuarelausers",
  "info": {
    "name": "acuarelauser",
    "description": ""
  },
  "options": {
    "increments": true,
    "timestamps": true,
    "draftAndPublish": true
  },
  "attributes": {
    "name": {
      "type": "string"
    },
    "lastname": {
      "type": "string"
    },
    "password": {
      "type": "password"
    },
    "mail": {
      "type": "email"
    },
    "creation_date": {
      "type": "datetime"
    },
    "photo": {
      "model": "file",
      "via": "related",
      "allowedTypes": [
        "images",
        "files",
        "videos"
      ],
      "plugin": "upload",
      "required": false
    },
    "status": {
      "type": "boolean"
    },
    "address": {
      "type": "string"
    },
    "country": {
      "type": "string"
    },
    "state": {
      "type": "string"
    },
    "city": {
      "type": "string"
    },
    "daycare": {
      "model": "daycare",
      "via": "acuarelausers"
    },
    "chats": {
      "collection": "chat",
      "via": "acuarelauser_2"
    },
    "supporttickets": {
      "collection": "supportticket",
      "via": "acuarelauser_admin"
    },
    "rols": {
      "collection": "rol",
      "via": "acuarelausers",
      "dominant": true
    },
    "events_invitation": {
      "collection": "event",
      "via": "acuarelausers_invited"
    },
    "group": {
      "model": "group",
      "via": "acuarelauser"
    },
    "relationships": {
      "collection": "relationship",
      "via": "acuarelauser"
    },
    "birthdate": {
      "type": "date"
    },
    "experience": {
      "type": "json"
    },
    "study": {
      "type": "string"
    },
    "hability": {
      "type": "string"
    },
    "certificate": {
      "type": "json"
    },
    "addressee": {
      "collection": "addressee",
      "via": "sender"
    },
    "addressees": {
      "collection": "addressee",
      "via": "acuarelausers"
    },
    "posts": {
      "collection": "post",
      "via": "acuarelauser"
    },
    "childminderinuser": {
      "collection": "checkin",
      "via": "asistente"
    },
    "guardianinuser": {
      "collection": "checkin",
      "via": "acudiente"
    },
    "childminderoutuser": {
      "collection": "checkout",
      "via": "asistente"
    },
    "guardianoutuser": {
      "collection": "checkout",
      "via": "acudiente"
    },
    "phone": {
      "type": "string"
    },
    "visits": {
      "collection": "visit",
      "via": "acuarelauser"
    },
    "comments": {
      "collection": "comment",
      "via": "acuarelauser"
    },
    "reactions": {
      "collection": "reaction",
      "via": "acuarelauser"
    },
    "movements": {
      "via": "payer",
      "collection": "movement"
    },
    "employee_payroll": {
      "via": "payroll",
      "collection": "movement"
    },
    "work_phone": {
      "type": "string"
    },
    "email": {
      "type": "email"
    },
    "work_place": {
      "type": "string"
    },
    "profession": {
      "type": "string"
    },
    "is_principal": {
      "type": "boolean"
    },
    "children": {
      "via": "acuarelausers",
      "collection": "children",
      "dominant": true
    },
    "end_demo": {
      "type": "date"
    },
    "certificates": {
      "type": "component",
      "repeatable": true,
      "component": "certificates.certificates"
    },
    "tokenpass": {
      "model": "tokens",
      "via": "acuarelauser"
    },
    "abilities": {
      "model": "abilities"
    },
    "paypalToken": {
      "type": "text",
      "default": "jHY8Y567hhFi793joJH"
    },
    "wizard_steps": {
      "type": "json"
    }
  }
}
