{
  "collectionName": "components_files_files",
  "info": {
    "name": "files",
    "icon": "server"
  },
  "options": {},
  "attributes": {
    "health_exam_form": {
      "model": "file",
      "via": "related",
      "allowedTypes": [
        "files",
        "images",
        "videos"
      ],
      "plugin": "upload",
      "required": false
    },
    "allergy_format": {
      "model": "file",
      "via": "related",
      "allowedTypes": [
        "files",
        "images",
        "videos"
      ],
      "plugin": "upload",
      "required": false
    },
    "identity_document": {
      "model": "file",
      "via": "related",
      "allowedTypes": [
        "files",
        "images",
        "videos"
      ],
      "plugin": "upload",
      "required": false
    },
    "parent_documents": {
      "model": "file",
      "via": "related",
      "allowedTypes": [
        "images",
        "files",
        "videos"
      ],
      "plugin": "upload",
      "required": false
    }
  }
}
